<?xml version="1.0" encoding="utf-8" ?><dwsync><file name="_functions.scss" server="honeydigital.co.uk/public_html/kenex/" local="3570013538" remote="3648505380" Dst="-1" /><file name="_variables.scss" server="honeydigital.co.uk/public_html/kenex/" local="3646727639" remote="3648505380" Dst="-1" /><file name="_typography.scss" server="honeydigital.co.uk/public_html/kenex/" local="3620713512" remote="3648505380" Dst="-1" /><file name="_print.scss" server="honeydigital.co.uk/public_html/kenex/" local="3570014028" remote="3648505380" Dst="-1" /><file name="_grid.scss" server="honeydigital.co.uk/public_html/kenex/" local="3620634738" remote="3648505380" Dst="-1" /><file name="_mixins.scss" server="honeydigital.co.uk/public_html/kenex/" local="3620721001" remote="3648505380" Dst="-1" /><file name="_ie_grid.scss" server="honeydigital.co.uk/public_html/kenex/" local="3570013594" remote="3648505380" Dst="-1" /><file name="_normalize.scss" server="honeydigital.co.uk/public_html/kenex/" local="3570018162" remote="3648505380" Dst="-1" /></dwsync>